batchcensusgeocode/__init__.py
batchcensusgeocode/geocode_batch.py
batchcensusgeocode-0.0.7.dist-info/METADATA
batchcensusgeocode-0.0.7.dist-info/WHEEL
batchcensusgeocode-0.0.7.dist-info/RECORD
